[
  {
    "username": "Jami",
    "acct": "Jami@mstdn.io",
    "display_name": "Jami",
    "avatar": "https://files.mastodon.social/cache/accounts/avatars/000/659/383/original/1f46890c8b06d84b.png",
    "header": "https://files.mastodon.social/cache/accounts/headers/000/659/383/original/3238b7dc7d805a88.png",
    "url": "https://mstdn.io/@Jami",
    "note": "<p>The distributed universal and secure Free Software for multimedia communications by Savoir-faire Linux and the GNU community.</p>",
    "domain": "mstdn.io",
    "langs": [
      "en"
    ],
    "tags": [
      "calls",
      "instant_messaging",
      "video_calls",
      "conferences"
    ],
    "base": null,
    "licenses": [
      "GPL-3.0-or-later"
    ],
    "repo": "https://git.jami.net/savoirfairelinux",
    "web": "https://jami.net"
  },
  {
    "username": "Jami",
    "acct": "Jami@mstdn.io",
    "display_name": "Jami",
    "avatar": "https://files.mastodon.social/cache/accounts/avatars/000/659/383/original/1f46890c8b06d84b.png",
    "header": "https://files.mastodon.social/cache/accounts/headers/000/659/383/original/3238b7dc7d805a88.png",
    "url": "https://mstdn.io/@Jami",
    "note": "<p>The distributed universal and secure Free Software for multimedia communications by Savoir-faire Linux and the GNU community.</p>",
    "domain": "mstdn.io",
    "langs": [
      "en"
    ],
    "tags": [
      "calls",
      "instant_messaging",
      "video_calls",
      "conferences"
    ],
    "base": null,
    "licenses": [
      "GPL-3.0-or-later"
    ],
    "repo": "https://git.jami.net/savoirfairelinux",
    "web": "https://jami.net"
  }
]