[
  {
    "username": "scummvm",
    "acct": "scummvm@corteximplant.com",
    "display_name": "ScummVM",
    "avatar": "https://files.mastodon.social/cache/accounts/avatars/109/873/584/227/547/897/original/c0d079dbafb90391.png",
    "header": "https://files.mastodon.social/cache/accounts/headers/109/873/584/227/547/897/original/0e269a038dd7c251.png",
    "url": "https://corteximplant.com/@scummvm",
    "note": "<p>ScummVM is a program which allows you to run certain classic graphical point-and-click adventure games and RPGs.</p>",
    "domain": "corteximplant.com",
    "langs": [
      "en"
    ],
    "tags": [
      "2d",
      "engine",
      "graphical_adventure"
    ],
    "base": null,
    "licenses": [
      "GPL-3.0-only"
    ],
    "repo": "https://github.com/scummvm",
    "web": "https://www.scummvm.org"
  },
  {
    "username": "scummvm",
    "acct": "scummvm@corteximplant.com",
    "display_name": "ScummVM",
    "avatar": "https://files.mastodon.social/cache/accounts/avatars/109/873/584/227/547/897/original/c0d079dbafb90391.png",
    "header": "https://files.mastodon.social/cache/accounts/headers/109/873/584/227/547/897/original/0e269a038dd7c251.png",
    "url": "https://corteximplant.com/@scummvm",
    "note": "<p>ScummVM is a program which allows you to run certain classic graphical point-and-click adventure games and RPGs.</p>",
    "domain": "corteximplant.com",
    "langs": [
      "en"
    ],
    "tags": [
      "2d",
      "engine",
      "graphical_adventure"
    ],
    "base": null,
    "licenses": [
      "GPL-3.0-only"
    ],
    "repo": "https://github.com/scummvm",
    "web": "https://www.scummvm.org"
  }
]